{
  "date": "2026-02-23",
  "articles": [
    {
      "title": "이제 남은 유일한 해자는 돈뿐인가?",
      "link": "https://news.hada.io/topic?id=26913",
      "published": "2026-02-23T09:59:31+09:00",
      "summary": "<ul>\n<li>\n<strong>AI가 대량 생산하는 시대</strong>에 인간의 창의적 사고 가치는 하락하고, <strong>인간의 관심(Attention)</strong> 은 희소 자원으로 부상</li>\n<li>새로운 제품을 만드는 것은 쉬워졌지만, <strong>관심을 얻는 것은 극도로 어려워진 환경</strong>으로 전환됨</li>\n<li>\n<strong>기존 채널(검색,...</p>",
      "category": "기술 뉴스",
      "source": "GeekNews - 개발/기술/스타트업 뉴스 서비스"
    },
    {
      "title": "코드 공장 시대와 미래 SRE",
      "link": "https://news.hada.io/topic?id=26912",
      "published": "2026-02-23T09:53:29+09:00",
      "summary": "<p>원래는 제 주변에만 공유한 졸문이나, 반응이 괜찮아서 Geeknews에도 공유하여 다른 분들의 생각과 관점을 듣고 싶어서 공유합니다. 홍보성 글로 생각되면 지적해 주십시오!</p>\n<hr />\n<h4>요약</h4>\n<ul>\n<li>소프트웨어 엔지니어링의 근간이 AI와 자동화의 급격한 부상으로 재구조화되고 있음. 이러한 변혁은 되돌",
      "category": "기술 뉴스",
      "source": "GeekNews - 개발/기술/스타트업 뉴스 서비스"
    },
    {
      "title": "ChatDev 2.0 - 멀티에이전트 협업 기반 Zero-Code 개발 플랫폼",
      "link": "https://news.hada.io/topic?id=26911",
      "published": "2026-02-23T09:51:01+09:00",
      "summary": "<ul>\n<li>\n<strong>코드 작성 없이 멀티에이전트 시스템을 구성·실행</strong>할 수 있도록 설계된 <strong>Zero-Code 플랫폼</strong>\n</li>\n<li>간단한 설정만으로 <strong>에이전트, 워크플로, 태스크를 정의</strong>해 데이터 시각화, 3D 생성, 심층 연구 등 복잡한 시나리오를 자동화 지원</li>\n<li>기존 <strong>...</p>",
      "category": "기술 뉴스",
      "source": "GeekNews - 개발/기술/스타트업 뉴스 서비스"
    },
    {
      "title": "이란 학생들, 유혈 진압 이후 첫 대규모 반정부 시위 벌여",
      "link": "https://news.hada.io/topic?id=26910",
      "published": "2026-02-23T09:46:01+09:00",
      "summary": "<ul>\n<li>이란 여러 대학에서 <strong>정부에 반대하는 학생 시위</strong>가 열렸으며, 이는 1월의 유혈 진압 이후 처음으로 대규모로 진행된 집회임</li>\n<li>테헤란의 <strong>Sharif 공과대학교</strong>를 비롯해 여러 대학에서 학생들이 행진하며 “독재자에게 죽음을” 등 <strong>반정부 구호</strong>를 외침...</p>",
      "category": "기술 뉴스",
      "source": "GeekNews - 개발/기술/스타트업 뉴스 서비스"
    },
    {
      "title": "가정용 e-paper 대시보드 Timeframe 개발기",
      "link": "https://news.hada.io/topic?id=26909",
      "published": "2026-02-23T09:43:01+09:00",
      "summary": "<ul>\n<li>\n<strong>집안에서 달력/날씨/스마트홈 정보를 표시하는 시스템</strong>을 만들기 위해 e-paper 기반 대시보드 <strong>Timeframe</strong>을 개발</li>\n<li>\n<strong>23인치 Boox Mira Pro</strong>의 실시간 업데이트 기능을 활용해 <strong>대형 화면과 실시간 상태 표시</strong> 가능</li>\n<li>백엔드는 ...</p>",
      "category": "기술 뉴스",
      "source": "GeekNews - 개발/기술/스타트업 뉴스 서비스"
    },
    {
      "title": "Apple might take a new approach to announcing its next products",
      "link": "https://techcrunch.com/2026/02/22/apple-might-take-a-new-approach-to-announcing-its-next-products/",
      "published": "Sun, 22 Feb 2026 23:08:08 +0000",
      "summary": "Apple has invited the tech press to a “special Apple experience” on March 4, but it might unfold a bit differently than the company's standard press event.",
      "category": "기술 뉴스",
      "source": "TechCrunch"
    },
    {
      "title": "Can the creator economy stay afloat in a flood of AI slop?",
      "link": "https://techcrunch.com/2026/02/22/can-the-creator-economy-stay-afloat-in-a-flood-of-ai-slop/",
      "published": "Sun, 22 Feb 2026 22:15:58 +0000",
      "summary": "On the latest episode of Equity, we debated what’s next for the creator economy, and whether there will be any room for the next generation of creators to stand out.",
      "category": "기술 뉴스",
      "source": "TechCrunch"
    },
    {
      "title": "Bill Gurley says that right now, the worst thing you can do for your career is play it safe",
      "link": "https://techcrunch.com/2026/02/22/bill-gurley-says-that-right-now-the-worst-thing-you-can-do-for-your-career-is-play-it-safe/",
      "published": "Sun, 22 Feb 2026 21:08:50 +0000",
      "summary": "\"The number one thing is to get out of your head this ideal that gets passed around in the self-help world: 'go get a mentor,' and everyone runs out and cold calls someone that's ridiculously too high and unachievable, and it doesn't work.\"",
      "category": "기술 뉴스",
      "source": "TechCrunch"
    },
    {
      "title": "Quantonation’s double-sized second fund shows quantum still has believers",
      "link": "https://techcrunch.com/2026/02/22/quantonations-double-sized-second-fund-shows-quantum-still-has-believers/",
      "published": "Sun, 22 Feb 2026 18:00:00 +0000",
      "summary": "Quantonation Ventures, a venture firm investing in quantum and physics-based startups, has closed its oversubscribed second fund at €220 million, or approximately $260 million. That’s more than twice the size of its inaugural fund, and comes in addition to other signals that the quantum winter isn’t",
      "category": "기술 뉴스",
      "source": "TechCrunch"
    },
    {
      "title": "Trump says Netflix will face ‘consequences’ if it doesn’t fire board member Susan Rice",
      "link": "https://techcrunch.com/2026/02/22/trump-says-netflix-will-face-consequences-if-it-doesnt-fire-board-member-susan-rice/",
      "published": "Sun, 22 Feb 2026 17:39:55 +0000",
      "summary": "Netflix board member Susan Rice had predicted that corporations that “take a knee” to Trump will be “held accountable” when Democrats return to power.",
      "category": "기술 뉴스",
      "source": "TechCrunch"
    },
    {
      "title": "I built Timeframe, our family e-paper dashboard",
      "link": "https://hawksley.org/2026/02/17/timeframe.html",
      "published": "Sun, 22 Feb 2026 19:12:31 +0000",
      "summary": "<a href=\"https://news.ycombinator.com/item?id=47113728\">Comments</a>",
      "category": "개발 트렌드",
      "source": "Hacker News"
    },
    {
      "title": "Google restricting Google AI Pro/Ultra subscribers for using OpenClaw",
      "link": "https://discuss.ai.google.dev/t/account-restricted-without-warning-google-ai-ultra-oauth-via-openclaw/122778",
      "published": "Sun, 22 Feb 2026 23:07:55 +0000",
      "summary": "<a href=\"https://news.ycombinator.com/item?id=47115805\">Comments</a>",
      "category": "개발 트렌드",
      "source": "Hacker News"
    },
    {
      "title": "Loops is a federated, open-source TikTok",
      "link": "https://joinloops.org/",
      "published": "Sun, 22 Feb 2026 18:56:40 +0000",
      "summary": "<a href=\"https://news.ycombinator.com/item?id=47113618\">Comments</a>",
      "category": "개발 트렌드",
      "source": "Hacker News"
    },
    {
      "title": "The surprising power of daily rituals",
      "link": "https://www.bbc.com/future/article/20210914-how-rituals-help-us-to-deal-with-uncertainty-and-stress",
      "published": "Mon, 23 Feb 2026 01:23:18 +0000",
      "summary": "<a href=\"https://news.ycombinator.com/item?id=47116866\">Comments</a>",
      "category": "개발 트렌드",
      "source": "Hacker News"
    },
    {
      "title": "Show HN: CIA World Factbook Archive (1990–2025), searchable and exportable",
      "link": "https://cia-factbook-archive.fly.dev/",
      "published": "Sun, 22 Feb 2026 20:50:23 +0000",
      "summary": "<a href=\"https://news.ycombinator.com/item?id=47114530\">Comments</a>",
      "category": "개발 트렌드",
      "source": "Hacker News"
    }
  ]
}